{"high":150,"data":[{"symbol":"ABINFRA","series":"SM","comapnyName":"A B Infrabuild Limited","new52WHL":85.5,"prev52WHL":84.9,"prevHLDate":"06-Sep-2024","ltp":84,"prevClose":"82.5","change":1.5,"pChange":1.8181818181818181},{"symbol":"AEROFLEX","series":"EQ","comapnyName":"Aeroflex Industries Limited","new52WHL":202.7,"prev52WHL":193.2,"prevHLDate":"06-Sep-2024","ltp":202.4,"prevClose":"186.07","change":16.33,"pChange":8.776266996291719},{"symbol":"AETHER","series":"EQ","comapnyName":"Aether Industries Limited","new52WHL":1071,"prev52WHL":1035.6,"prevHLDate":"12-Sep-2023","ltp":1062,"prevClose":"974.5","change":87.5,"pChange":8.978963571062083},{"symbol":"AISL","series":"SM","comapnyName":"ANI Integrated Services Limited","new52WHL":167.7,"prev52WHL":164.7,"prevHLDate":"09-Sep-2024","ltp":167.7,"prevClose":"161.65","change":6.05,"pChange":3.742653881843489},{"symbol":"AJANTPHARM","series":"EQ","comapnyName":"Ajanta Pharma Limited","new52WHL":3473.7,"prev52WHL":3409.4,"prevHLDate":"06-Sep-2024","ltp":3402.5,"prevClose":"3297","change":105.5,"pChange":3.199878677585684},{"symbol":"AKZOINDIA","series":"EQ","comapnyName":"Akzo Nobel India Limited","new52WHL":3971.25,"prev52WHL":3855,"prevHLDate":"06-Sep-2024","ltp":3826.5,"prevClose":"3776.9","change":49.6,"pChange":1.3132463131139294},{"symbol":"ALKEM","series":"EQ","comapnyName":"Alkem Laboratories Limited","new52WHL":6375,"prev52WHL":6346.7,"prevHLDate":"06-Sep-2024","ltp":6311,"prevClose":"6268.05","change":42.95,"pChange":0.6852210815165801},{"symbol":"ANIKINDS","series":"BE","comapnyName":"Anik Industries Limited","new52WHL":91.35,"prev52WHL":88.12,"prevHLDate":"09-Sep-2024","ltp":91.35,"prevClose":"87","change":4.35,"pChange":5},{"symbol":"BALUFORGE","series":"EQ","comapnyName":"Balu Forge Industries Limited","new52WHL":866.5,"prev52WHL":866.35,"prevHLDate":"09-Sep-2024","ltp":837.7,"prevClose":"854.35","change":-16.65,"pChange":-1.9488500029262013},{"symbol":"BASML","series":"EQ","comapnyName":"Bannari Amman Spinning Mills Limited","new52WHL":69.5,"prev52WHL":65.96,"prevHLDate":"05-Sep-2024","ltp":68.01,"prevClose":"61.9","change":6.11,"pChange":9.87075928917609},{"symbol":"BETA","series":"SM","comapnyName":"Beta Drugs Limited","new52WHL":1985,"prev52WHL":1860,"prevHLDate":"05-Sep-2024","ltp":1837,"prevClose":"1710.25","change":126.75,"pChange":7.411197193392779},{"symbol":"BHAGERIA","series":"EQ","comapnyName":"Bhageria Industries Limited","new52WHL":270.89,"prev52WHL":257.35,"prevHLDate":"05-Sep-2024","ltp":256.95,"prevClose":"246.01","change":10.94,"pChange":4.446973700256087},{"symbol":"BRITANNIA","series":"EQ","comapnyName":"Britannia Industries Limited","new52WHL":6010,"prev52WHL":6005,"prevHLDate":"23-Jul-2024","ltp":5959,"prevClose":"5939.45","change":19.55,"pChange":0.3291550564446203},{"symbol":"CCCL","series":"EQ","comapnyName":"Consolidated Construction Consortium Limited","new52WHL":14.59,"prev52WHL":13.9,"prevHLDate":"09-Sep-2024","ltp":14.59,"prevClose":"13.9","change":0.69,"pChange":4.9640287769784175},{"symbol":"CELLECOR","series":"SM","comapnyName":"Cellecor Gadgets Limited","new52WHL":52.05,"prev52WHL":49.6,"prevHLDate":"09-Sep-2024","ltp":47.15,"prevClose":"49.6","change":-2.45,"pChange":-4.939516129032258},{"symbol":"CENTURYTEX","series":"EQ","comapnyName":"Century Textiles & Industries Limited","new52WHL":2530,"prev52WHL":2525,"prevHLDate":"27-Aug-2024","ltp":2487,"prevClose":"2355","change":132,"pChange":5.6050955414012735},{"symbol":"CHAVDA","series":"SM","comapnyName":"Chavda Infra Limited","new52WHL":204.9,"prev52WHL":200.05,"prevHLDate":"09-Sep-2024","ltp":201.5,"prevClose":"188.95","change":12.55,"pChange":6.64196877480815},{"symbol":"CHOICEIN","series":"EQ","comapnyName":"Choice International Limited","new52WHL":467.45,"prev52WHL":461.4,"prevHLDate":"05-Sep-2024","ltp":458,"prevClose":"446.3","change":11.7,"pChange":2.6215550078422587},{"symbol":"CLEDUCATE","series":"EQ","comapnyName":"CL Educate Limited","new52WHL":128.4,"prev52WHL":123.79,"prevHLDate":"09-Sep-2024","ltp":119.95,"prevClose":"123.04","change":-3.09,"pChange":-2.5113784135240573},{"symbol":"COFORGE","series":"EQ","comapnyName":"Coforge Limited","new52WHL":6872.8,"prev52WHL":6847.45,"prevHLDate":"19-Feb-2024","ltp":6799.95,"prevClose":"6490.75","change":309.2,"pChange":4.763702191580326},{"symbol":"CONCORDBIO","series":"EQ","comapnyName":"Concord Biotech Limited","new52WHL":1920,"prev52WHL":1914.45,"prevHLDate":"06-Sep-2024","ltp":1904,"prevClose":"1854.4","change":49.6,"pChange":2.6747195858498705},{"symbol":"CONSUMIETF","series":"EQ","comapnyName":"ICICI Prudential Nifty India Consumption ETF","new52WHL":126.12,"prev52WHL":124.99,"prevHLDate":"09-Sep-2024","ltp":125.83,"prevClose":"124.9","change":0.93,"pChange":0.7445956765412329},{"symbol":"CONTI","series":"ST","comapnyName":"Continental Seeds and Chemicals Limited","new52WHL":66.85,"prev52WHL":66.15,"prevHLDate":"22-Aug-2024","ltp":66.85,"prevClose":"63.7","change":3.15,"pChange":4.945054945054945},{"symbol":"DABUR","series":"EQ","comapnyName":"Dabur India Limited","new52WHL":669.9,"prev52WHL":664.9,"prevHLDate":"09-Sep-2024","ltp":663.6,"prevClose":"662.35","change":1.25,"pChange":0.18872197478674416},{"symbol":"DCW","series":"EQ","comapnyName":"DCW Limited","new52WHL":103.65,"prev52WHL":100.3,"prevHLDate":"09-Sep-2024","ltp":100.8,"prevClose":"99.52","change":1.28,"pChange":1.2861736334405145},{"symbol":"DESTINY","series":"ST","comapnyName":"Destiny Logistics & Infra Limited","new52WHL":66.65,"prev52WHL":63.5,"prevHLDate":"09-Sep-2024","ltp":66.65,"prevClose":"63.5","change":3.15,"pChange":4.960629921259843},{"symbol":"DHUNINV","series":"EQ","comapnyName":"Dhunseri Investments Limited","new52WHL":2289.05,"prev52WHL":1977.9,"prevHLDate":"09-Sep-2024","ltp":2261.1,"prevClose":"1911.85","change":349.25,"pChange":18.267646520386013},{"symbol":"DIVISLAB","series":"EQ","comapnyName":"Divi's Laboratories Limited","new52WHL":5447.35,"prev52WHL":5194.3,"prevHLDate":"09-Sep-2024","ltp":5444,"prevClose":"5173.5","change":270.5,"pChange":5.228568667246545},{"symbol":"DJML","series":"BE","comapnyName":"DJ Mediaprint & Logistics Limited","new52WHL":132.26,"prev52WHL":128.5,"prevHLDate":"09-Sep-2024","ltp":132.26,"prevClose":"125.97","change":6.29,"pChange":4.993252361673414},{"symbol":"DMART","series":"EQ","comapnyName":"Avenue Supermarts Limited","new52WHL":5422.45,"prev52WHL":5395,"prevHLDate":"09-Sep-2024","ltp":5338,"prevClose":"5361.4","change":-23.4,"pChange":-0.43645316521804006},{"symbol":"DOLATALGO","series":"EQ","comapnyName":"Dolat Algotech Limited","new52WHL":184.4,"prev52WHL":178.4,"prevHLDate":"05-Sep-2024","ltp":182.6,"prevClose":"171.91","change":10.69,"pChange":6.218370077366064},{"symbol":"DOMS","series":"EQ","comapnyName":"DOMS Industries Limited","new52WHL":2793.9,"prev52WHL":2774.6,"prevHLDate":"09-Sep-2024","ltp":2734.15,"prevClose":"2732.05","change":2.1,"pChange":0.07686535751541883},{"symbol":"ECOSMOBLTY","series":"EQ","comapnyName":"Ecos (India) Mobility & Hospitality Limited","new52WHL":524.65,"prev52WHL":497.4,"prevHLDate":"09-Sep-2024","ltp":491.95,"prevClose":"481.9","change":10.05,"pChange":2.0854949159576677},{"symbol":"EFACTOR","series":"SM","comapnyName":"E Factor Experiences Limited","new52WHL":265,"prev52WHL":260,"prevHLDate":"04-Jul-2024","ltp":258.6,"prevClose":"223","change":35.6,"pChange":15.964125560538116},{"symbol":"EPACK","series":"EQ","comapnyName":"EPACK Durable Limited","new52WHL":302.7,"prev52WHL":292.4,"prevHLDate":"09-Sep-2024","ltp":299.5,"prevClose":"280.65","change":18.85,"pChange":6.716550864065562},{"symbol":"EPIGRAL","series":"EQ","comapnyName":"Epigral Limited","new52WHL":2178.65,"prev52WHL":2026,"prevHLDate":"22-Aug-2024","ltp":2155.15,"prevClose":"1849.7","change":305.45,"pChange":16.513488673839},{"symbol":"ESFL","series":"SM","comapnyName":"Essen Speciality Films Limited","new52WHL":362.9,"prev52WHL":345.65,"prevHLDate":"09-Sep-2024","ltp":362.9,"prevClose":"345.65","change":17.25,"pChange":4.990597425141039},{"symbol":"EXCELINDUS","series":"EQ","comapnyName":"Excel Industries Limited","new52WHL":1634.95,"prev52WHL":1632,"prevHLDate":"05-Sep-2024","ltp":1625,"prevClose":"1496.9","change":128.1,"pChange":8.557685884160598},{"symbol":"FDC","series":"EQ","comapnyName":"FDC Limited","new52WHL":603.8,"prev52WHL":589.85,"prevHLDate":"09-Sep-2024","ltp":577.95,"prevClose":"562.75","change":15.2,"pChange":2.7010217681030655},{"symbol":"FLEXITUFF","series":"BE","comapnyName":"Flexituff Ventures International Limited","new52WHL":86.4,"prev52WHL":82.29,"prevHLDate":"09-Sep-2024","ltp":86.4,"prevClose":"82.29","change":4.11,"pChange":4.994531534815895},{"symbol":"FLUOROCHEM","series":"EQ","comapnyName":"Gujarat Fluorochemicals Limited","new52WHL":4012,"prev52WHL":4010,"prevHLDate":"09-Sep-2024","ltp":3925,"prevClose":"3976.5","change":-51.5,"pChange":-1.295108763988432},{"symbol":"FMCGIETF","series":"EQ","comapnyName":"ICICI PRUDENTIAL MUTUAL FUND - ICICI Prudential Nifty FMCG ETF","new52WHL":68,"prev52WHL":67.95,"prevHLDate":"05-Jun-2024","ltp":67.82,"prevClose":"67.6","change":0.22,"pChange":0.3254437869822485},{"symbol":"FOCE","series":"SM","comapnyName":"Foce India Limited","new52WHL":1620,"prev52WHL":1575,"prevHLDate":"09-Sep-2024","ltp":1520,"prevClose":"1557.5","change":-37.5,"pChange":-2.407704654895666},{"symbol":"GALAPREC","series":"BE","comapnyName":"Gala Precision Engineering Limited","new52WHL":774,"prev52WHL":757.15,"prevHLDate":"09-Sep-2024","ltp":739,"prevClose":"757.15","change":-18.15,"pChange":-2.3971471967245592},{"symbol":"GILLETTE","series":"EQ","comapnyName":"Gillette India Limited","new52WHL":9495,"prev52WHL":9425,"prevHLDate":"06-Sep-2024","ltp":9029,"prevClose":"9113.95","change":-84.95,"pChange":-0.9320876239171819},{"symbol":"GLOBALVECT","series":"BE","comapnyName":"Global Vectra Helicorp Limited","new52WHL":317.15,"prev52WHL":310.31,"prevHLDate":"30-Jul-2024","ltp":317.15,"prevClose":"302.05","change":15.1,"pChange":4.999172322463169},{"symbol":"GLOBUSSPR","series":"EQ","comapnyName":"Globus Spirits Limited","new52WHL":1288.4,"prev52WHL":1164,"prevHLDate":"03-Sep-2024","ltp":1235,"prevClose":"1090.4","change":144.6,"pChange":13.26118855465884},{"symbol":"GLS","series":"EQ","comapnyName":"Glenmark Life Sciences Limited","new52WHL":1299,"prev52WHL":1220,"prevHLDate":"09-Sep-2024","ltp":1294.75,"prevClose":"1204.95","change":89.8,"pChange":7.452591393833769},{"symbol":"GRCL","series":"SM","comapnyName":"Gayatri Rubbers And Chemicals Limited","new52WHL":425,"prev52WHL":420,"prevHLDate":"01-Aug-2024","ltp":420,"prevClose":"405.5","change":14.5,"pChange":3.5758323057953145},{"symbol":"GULFPETRO","series":"EQ","comapnyName":"GP Petroleums Limited","new52WHL":92.74,"prev52WHL":90.2,"prevHLDate":"05-Mar-2024","ltp":88.5,"prevClose":"87.65","change":0.85,"pChange":0.9697661152310325},{"symbol":"HCG","series":"EQ","comapnyName":"Healthcare Global Enterprises Limited","new52WHL":419.5,"prev52WHL":415,"prevHLDate":"05-Sep-2024","ltp":416,"prevClose":"402.65","change":13.35,"pChange":3.315534583385074},{"symbol":"HDFCLOWVOL","series":"EQ","comapnyName":"HDFC Mutual Fund - HDFC NIFTY100 Low Volatility 30 ETF","new52WHL":22,"prev52WHL":21.87,"prevHLDate":"02-Sep-2024","ltp":21,"prevClose":"21.02","change":-0.02,"pChange":-0.09514747859181731},{"symbol":"HIGREEN","series":"SM","comapnyName":"Hi-Green Carbon Limited","new52WHL":294.8,"prev52WHL":279.45,"prevHLDate":"09-Sep-2024","ltp":258.1,"prevClose":"271.95","change":-13.85,"pChange":-5.092847949990807},{"symbol":"HITECH","series":"EQ","comapnyName":"Hi-Tech Pipes Limited","new52WHL":197.5,"prev52WHL":197,"prevHLDate":"28-Aug-2024","ltp":191.1,"prevClose":"191.45","change":-0.35,"pChange":-0.18281535648994515},{"symbol":"HONASA","series":"EQ","comapnyName":"Honasa Consumer Limited","new52WHL":547,"prev52WHL":538.75,"prevHLDate":"06-Sep-2024","ltp":543.5,"prevClose":"519.8","change":23.7,"pChange":4.559445940746441},{"symbol":"HRHNEXT","series":"SM","comapnyName":"HRH Next Services Limited","new52WHL":83.2,"prev52WHL":79.25,"prevHLDate":"09-Sep-2024","ltp":83.2,"prevClose":"79.25","change":3.95,"pChange":4.9842271293375395},{"symbol":"HSCL","series":"EQ","comapnyName":"Himadri Speciality Chemical Limited","new52WHL":567,"prev52WHL":556,"prevHLDate":"02-Sep-2024","ltp":564,"prevClose":"530.25","change":33.75,"pChange":6.364922206506365},{"symbol":"ICRA","series":"EQ","comapnyName":"ICRA Limited","new52WHL":6505,"prev52WHL":6450,"prevHLDate":"24-May-2024","ltp":6495,"prevClose":"6182.55","change":312.45,"pChange":5.053739961666302},{"symbol":"IEX","series":"EQ","comapnyName":"Indian Energy Exchange Limited","new52WHL":217.3,"prev52WHL":213.94,"prevHLDate":"09-Sep-2024","ltp":214.61,"prevClose":"213.52","change":1.09,"pChange":0.5104908205320344},{"symbol":"INDHOTEL","series":"EQ","comapnyName":"The Indian Hotels Company Limited","new52WHL":696.7,"prev52WHL":673.5,"prevHLDate":"05-Sep-2024","ltp":695.5,"prevClose":"665.85","change":29.65,"pChange":4.452954869715401},{"symbol":"INDOSTAR","series":"EQ","comapnyName":"IndoStar Capital Finance Limited","new52WHL":304,"prev52WHL":298.35,"prevHLDate":"28-Aug-2024","ltp":294,"prevClose":"286","change":8,"pChange":2.797202797202797},{"symbol":"INDOTHAI","series":"BE","comapnyName":"Indo Thai Securities Limited","new52WHL":591.85,"prev52WHL":563.7,"prevHLDate":"09-Sep-2024","ltp":591.85,"prevClose":"563.7","change":28.15,"pChange":4.9937910235941105},{"symbol":"INOXWIND","series":"EQ","comapnyName":"Inox Wind Limited","new52WHL":246,"prev52WHL":237,"prevHLDate":"28-Aug-2024","ltp":241.05,"prevClose":"234.06","change":6.99,"pChange":2.9864137400666495},{"symbol":"INTERARCH","series":"EQ","comapnyName":"Interarch Building Products Limited","new52WHL":1319.95,"prev52WHL":1314.8,"prevHLDate":"26-Aug-2024","ltp":1277,"prevClose":"1208.6","change":68.4,"pChange":5.659440675161344},{"symbol":"IRIS","series":"BE","comapnyName":"Iris Business Services Limited","new52WHL":295.01,"prev52WHL":286.11,"prevHLDate":"29-Jul-2024","ltp":295.01,"prevClose":"280.97","change":14.04,"pChange":4.996974765989251},{"symbol":"JEYYAM","series":"ST","comapnyName":"Jeyyam Global Foods Limited","new52WHL":64.65,"prev52WHL":64.05,"prevHLDate":"09-Sep-2024","ltp":61,"prevClose":"64.05","change":-3.05,"pChange":-4.761904761904762},{"symbol":"JKCEMENT","series":"EQ","comapnyName":"JK Cement Limited","new52WHL":4895.5,"prev52WHL":4830,"prevHLDate":"09-Sep-2024","ltp":4715,"prevClose":"4807.75","change":-92.75,"pChange":-1.9291768498778015},{"symbol":"JSLL","series":"SM","comapnyName":"Jeena Sikho Lifecare Limited","new52WHL":1530,"prev52WHL":1519,"prevHLDate":"09-Sep-2024","ltp":1455,"prevClose":"1499.7","change":-44.7,"pChange":-2.980596119223845},{"symbol":"JUBLFOOD","series":"EQ","comapnyName":"Jubilant Foodworks Limited","new52WHL":671.3,"prev52WHL":667.65,"prevHLDate":"28-Aug-2024","ltp":664.6,"prevClose":"642.4","change":22.2,"pChange":3.455790784557908},{"symbol":"JUBLINDS","series":"EQ","comapnyName":"Jubilant Industries Limited","new52WHL":1947,"prev52WHL":1916.3,"prevHLDate":"09-Sep-2024","ltp":1810,"prevClose":"1898.95","change":-88.95,"pChange":-4.684167566286632},{"symbol":"KAMOPAINTS","series":"EQ","comapnyName":"Kamdhenu Ventures Limited","new52WHL":49.66,"prev52WHL":49,"prevHLDate":"24-Jan-2024","ltp":49.53,"prevClose":"48.55","change":0.98,"pChange":2.018537590113285},{"symbol":"KDL","series":"ST","comapnyName":"Kore Digital Limited","new52WHL":2590.65,"prev52WHL":2533.55,"prevHLDate":"26-Aug-2024","ltp":2590.65,"prevClose":"2467.3","change":123.35,"pChange":4.999392047987679},{"symbol":"KEEPLEARN","series":"BE","comapnyName":"DSJ Keep Learning Limited","new52WHL":5.07,"prev52WHL":4.83,"prevHLDate":"09-Sep-2024","ltp":5.07,"prevClose":"4.83","change":0.24,"pChange":4.968944099378882},{"symbol":"KHFM","series":"SM","comapnyName":"Khfm Hospitality And Facility Management Services Limited","new52WHL":97.9,"prev52WHL":96.95,"prevHLDate":"09-Sep-2024","ltp":94,"prevClose":"96.95","change":-2.95,"pChange":-3.042805569881382},{"symbol":"KIMS","series":"EQ","comapnyName":"Krishna Institute of Medical Sciences Limited","new52WHL":2694,"prev52WHL":2694,"prevHLDate":"05-Sep-2024","ltp":2665,"prevClose":"2633.75","change":31.25,"pChange":1.1865211200759374},{"symbol":"KITEX","series":"EQ","comapnyName":"Kitex Garments Limited","new52WHL":504.8,"prev52WHL":488.4,"prevHLDate":"09-Sep-2024","ltp":470,"prevClose":"488.4","change":-18.4,"pChange":-3.7674037674037675},{"symbol":"KSCL","series":"EQ","comapnyName":"Kaveri Seed Company Limited","new52WHL":1201,"prev52WHL":1180,"prevHLDate":"12-Aug-2024","ltp":1180,"prevClose":"1163.85","change":16.15,"pChange":1.3876358637281436},{"symbol":"LAURUSLABS","series":"EQ","comapnyName":"Laurus Labs Limited","new52WHL":518,"prev52WHL":501.3,"prevHLDate":"05-Sep-2024","ltp":507,"prevClose":"490.95","change":16.05,"pChange":3.269172013443324},{"symbol":"LEMERITE","series":"SM","comapnyName":"Le Merite Exports Limited","new52WHL":212,"prev52WHL":210.7,"prevHLDate":"09-Sep-2024","ltp":207.1,"prevClose":"209.95","change":-2.85,"pChange":-1.3574660633484164},{"symbol":"LINCOLN","series":"EQ","comapnyName":"Lincoln Pharmaceuticals Limited","new52WHL":811.85,"prev52WHL":804.45,"prevHLDate":"05-Sep-2024","ltp":786.8,"prevClose":"771.55","change":15.25,"pChange":1.9765407296999546},{"symbol":"LIQUID1","series":"EQ","comapnyName":"Kotak Mahindra Mutual Fund - Kotak Nifty 1D Rate Liquid ETF","new52WHL":1120,"prev52WHL":1050.29,"prevHLDate":"28-Aug-2024","ltp":1007.43,"prevClose":"1007.27","change":0.16,"pChange":0.01588451954292295},{"symbol":"LIQUIDSBI","series":"EQ","comapnyName":"SBI Mutual Fund - SBI NIFTY 1D Rate ETF","new52WHL":1000.01,"prev52WHL":1000.01,"prevHLDate":"09-Sep-2024","ltp":1000.01,"prevClose":"999.99","change":0.02,"pChange":0.002000020000200002},{"symbol":"LIQUIDSHRI","series":"EQ","comapnyName":"Shriram Mutual Fund -SHRIRAM NIFTY 1D RATE LIQUID ETF","new52WHL":1011.72,"prev52WHL":1011.56,"prevHLDate":"09-Sep-2024","ltp":1011.72,"prevClose":"1011.55","change":0.17,"pChange":0.016805891948000595},{"symbol":"LRRPL","series":"ST","comapnyName":"Lead Reclaim And Rubber Products Limited","new52WHL":97.2,"prev52WHL":92.6,"prevHLDate":"09-Sep-2024","ltp":97.2,"prevClose":"92.6","change":4.6,"pChange":4.967602591792657},{"symbol":"LXCHEM","series":"EQ","comapnyName":"Laxmi Organic Industries Limited","new52WHL":323.2,"prev52WHL":316.85,"prevHLDate":"06-Sep-2024","ltp":319.5,"prevClose":"313.2","change":6.3,"pChange":2.0114942528735633},{"symbol":"MAHASTEEL","series":"BE","comapnyName":"Mahamaya Steel Industries Limited","new52WHL":205.29,"prev52WHL":197.99,"prevHLDate":"09-Sep-2024","ltp":205.29,"prevClose":"195.52","change":9.77,"pChange":4.9969312602291325},{"symbol":"MANORG","series":"BE","comapnyName":"Mangalam Organics Limited","new52WHL":720,"prev52WHL":694.3,"prevHLDate":"09-Sep-2024","ltp":672.9,"prevClose":"693.95","change":-21.05,"pChange":-3.033359752143526},{"symbol":"METROPOLIS","series":"EQ","comapnyName":"Metropolis Healthcare Limited","new52WHL":2196.65,"prev52WHL":2189.55,"prevHLDate":"06-Sep-2024","ltp":2162.3,"prevClose":"2153.65","change":8.65,"pChange":0.4016437211246024},{"symbol":"MIDQ50ADD","series":"EQ","comapnyName":"DSP  Mutual Fund - DSP Nifty Midcap 150 Quality 50 ETF","new52WHL":265.75,"prev52WHL":263.9,"prevHLDate":"05-Sep-2024","ltp":262.24,"prevClose":"258.03","change":4.21,"pChange":1.6315932255939232},{"symbol":"MODIRUBBER","series":"EQ","comapnyName":"Modi Rubber Limited","new52WHL":154.54,"prev52WHL":147.19,"prevHLDate":"09-Sep-2024","ltp":154.54,"prevClose":"147.19","change":7.35,"pChange":4.993545757184592},{"symbol":"MONARCH","series":"EQ","comapnyName":"Monarch Networth Capital Limited","new52WHL":919,"prev52WHL":913.5,"prevHLDate":"09-Sep-2024","ltp":885,"prevClose":"906.8","change":-21.8,"pChange":-2.404058226731363},{"symbol":"MOREPENLAB","series":"EQ","comapnyName":"Morepen Laboratories Limited","new52WHL":100.9,"prev52WHL":97.6,"prevHLDate":"09-Sep-2024","ltp":96.1,"prevClose":"94.03","change":2.07,"pChange":2.2014250771030524},{"symbol":"MOS","series":"SM","comapnyName":"Mos Utility Limited","new52WHL":302,"prev52WHL":301.9,"prevHLDate":"09-Sep-2024","ltp":290,"prevClose":"288.05","change":1.95,"pChange":0.6769658045478215},{"symbol":"MSPL","series":"EQ","comapnyName":"MSP Steel & Power Limited","new52WHL":48.94,"prev52WHL":47.02,"prevHLDate":"09-Sep-2024","ltp":46.9,"prevClose":"47.02","change":-0.12,"pChange":-0.25521054870267973},{"symbol":"NDL","series":"EQ","comapnyName":"Nandan Denim Limited","new52WHL":65.03,"prev52WHL":64.77,"prevHLDate":"09-Sep-2024","ltp":61.78,"prevClose":"64.1","change":-2.32,"pChange":-3.6193447737909517},{"symbol":"NORBTEAEXP","series":"EQ","comapnyName":"Norben Tea & Exports Limited","new52WHL":18.77,"prev52WHL":17.88,"prevHLDate":"09-Sep-2024","ltp":18.77,"prevClose":"17.88","change":0.89,"pChange":4.977628635346756},{"symbol":"ORIENTHOT","series":"EQ","comapnyName":"Oriental Hotels Limited","new52WHL":178.8,"prev52WHL":165,"prevHLDate":"30-Aug-2024","ltp":178.7,"prevClose":"156.7","change":22,"pChange":14.039566049776644},{"symbol":"OSWALAGRO","series":"BE","comapnyName":"Oswal Agro Mills Limited","new52WHL":72.67,"prev52WHL":69.45,"prevHLDate":"13-Aug-2024","ltp":71.8,"prevClose":"69.21","change":2.59,"pChange":3.742233781245485},{"symbol":"PANACEABIO","series":"EQ","comapnyName":"Panacea Biotec Limited","new52WHL":286.4,"prev52WHL":270.51,"prevHLDate":"09-Sep-2024","ltp":282.6,"prevClose":"270.51","change":12.09,"pChange":4.469335699234779},{"symbol":"PASUPTAC","series":"EQ","comapnyName":"Pasupati Acrylon Limited","new52WHL":65.83,"prev52WHL":57.28,"prevHLDate":"09-Sep-2024","ltp":63.3,"prevClose":"54.86","change":8.44,"pChange":15.384615384615385},{"symbol":"PCJEWELLER","series":"EQ","comapnyName":"PC Jeweller Limited","new52WHL":134.4,"prev52WHL":129.26,"prevHLDate":"09-Sep-2024","ltp":126.12,"prevClose":"129.26","change":-3.14,"pChange":-2.4292124400433237},{"symbol":"PGEL","series":"EQ","comapnyName":"PG Electroplast Limited","new52WHL":647.7,"prev52WHL":624,"prevHLDate":"09-Sep-2024","ltp":620,"prevClose":"613.9","change":6.1,"pChange":0.9936471738068089},{"symbol":"PIIND","series":"EQ","comapnyName":"PI Industries Limited","new52WHL":4701,"prev52WHL":4660.95,"prevHLDate":"06-Sep-2024","ltp":4694.8,"prevClose":"4617.25","change":77.55,"pChange":1.6795711733174508},{"symbol":"PPLPHARMA","series":"EQ","comapnyName":"Piramal Pharma Limited","new52WHL":239.8,"prev52WHL":228,"prevHLDate":"06-Sep-2024","ltp":239,"prevClose":"217.34","change":21.66,"pChange":9.965951964663661},{"symbol":"PRECWIRE","series":"EQ","comapnyName":"Precision Wires India Limited","new52WHL":203,"prev52WHL":198.8,"prevHLDate":"26-Aug-2024","ltp":195.8,"prevClose":"182.97","change":12.83,"pChange":7.01207848281139},{"symbol":"PREMIERENE","series":"EQ","comapnyName":"Premier Energies Limited","new52WHL":1267.95,"prev52WHL":1235,"prevHLDate":"09-Sep-2024","ltp":1162,"prevClose":"1208.65","change":-46.65,"pChange":-3.859678153311546},{"symbol":"PRSMJOHNSN","series":"EQ","comapnyName":"Prism Johnson Limited","new52WHL":208.8,"prev52WHL":199,"prevHLDate":"09-Feb-2024","ltp":208.8,"prevClose":"174","change":34.8,"pChange":20},{"symbol":"RADHIKAJWE","series":"EQ","comapnyName":"Radhika Jeweltech Limited","new52WHL":134.1,"prev52WHL":127.72,"prevHLDate":"09-Sep-2024","ltp":121.33,"prevClose":"127.72","change":-6.39,"pChange":-5.0031318509238965},{"symbol":"RBMINFRA","series":"SM","comapnyName":"Rbm Infracon Limited","new52WHL":840.5,"prev52WHL":821.7,"prevHLDate":"22-Aug-2024","ltp":840.5,"prevClose":"800.5","change":40,"pChange":4.996876951905059},{"symbol":"RELIGARE","series":"EQ","comapnyName":"Religare Enterprises Limited","new52WHL":296.15,"prev52WHL":288,"prevHLDate":"09-Sep-2024","ltp":292,"prevClose":"285.25","change":6.75,"pChange":2.366345311130587},{"symbol":"RELTD","series":"EQ","comapnyName":"Ravindra Energy Limited","new52WHL":94.33,"prev52WHL":91.49,"prevHLDate":"30-Jul-2024","ltp":94.33,"prevClose":"89.84","change":4.49,"pChange":4.997773820124666},{"symbol":"RMDRIP","series":"SM","comapnyName":"R M Drip and Sprinklers Systems Limited","new52WHL":230,"prev52WHL":225,"prevHLDate":"09-Sep-2024","ltp":228.85,"prevClose":"225","change":3.85,"pChange":1.711111111111111},{"symbol":"RPEL","series":"EQ","comapnyName":"Raghav Productivity Enhancers Limited","new52WHL":1258.45,"prev52WHL":1240,"prevHLDate":"27-Aug-2024","ltp":1186.5,"prevClose":"1154.95","change":31.55,"pChange":2.731719987878263},{"symbol":"RPGLIFE","series":"EQ","comapnyName":"RPG Life Sciences Limited","new52WHL":2422,"prev52WHL":2400,"prevHLDate":"09-Sep-2024","ltp":2382.1,"prevClose":"2378.45","change":3.65,"pChange":0.15346128781349197},{"symbol":"SARDAEN","series":"EQ","comapnyName":"Sarda Energy & Minerals Limited","new52WHL":369.95,"prev52WHL":368.9,"prevHLDate":"27-Aug-2024","ltp":368.95,"prevClose":"354.05","change":14.9,"pChange":4.208445134867956},{"symbol":"SCML","series":"SM","comapnyName":"Sharp Chucks and Machines Limited","new52WHL":138,"prev52WHL":136.4,"prevHLDate":"16-Jul-2024","ltp":136.75,"prevClose":"130.1","change":6.65,"pChange":5.111452728670254},{"symbol":"SENCO","series":"EQ","comapnyName":"Senco Gold Limited","new52WHL":1265,"prev52WHL":1251.45,"prevHLDate":"09-Sep-2024","ltp":1256.95,"prevClose":"1222.7","change":34.25,"pChange":2.801177721436166},{"symbol":"SEPC","series":"EQ","comapnyName":"SEPC Limited","new52WHL":32.69,"prev52WHL":31.64,"prevHLDate":"09-Sep-2024","ltp":32.26,"prevClose":"30.28","change":1.98,"pChange":6.538969616908851},{"symbol":"SEQUENT","series":"EQ","comapnyName":"Sequent Scientific Limited","new52WHL":184.7,"prev52WHL":184,"prevHLDate":"05-Sep-2024","ltp":179.9,"prevClose":"176.01","change":3.89,"pChange":2.2101016987671156},{"symbol":"SETUINFRA","series":"BZ","comapnyName":"Setubandhan Infrastructure Limited","new52WHL":1.16,"prev52WHL":1.16,"prevHLDate":"09-Sep-2024","ltp":1.06,"prevClose":"1.12","change":-0.06,"pChange":-5.357142857142857},{"symbol":"SHILPAMED","series":"EQ","comapnyName":"Shilpa Medicare Limited","new52WHL":855.9,"prev52WHL":854.1,"prevHLDate":"05-Sep-2024","ltp":837.9,"prevClose":"831.75","change":6.15,"pChange":0.739404869251578},{"symbol":"SHK","series":"EQ","comapnyName":"S H Kelkar and Company Limited","new52WHL":262.5,"prev52WHL":256.2,"prevHLDate":"30-Aug-2024","ltp":257.8,"prevClose":"243.64","change":14.16,"pChange":5.811853554424561},{"symbol":"SHRIPISTON","series":"EQ","comapnyName":"Shriram Pistons & Rings Limited","new52WHL":2369.2,"prev52WHL":2284.7,"prevHLDate":"06-Sep-2024","ltp":2354.15,"prevClose":"2206.15","change":148,"pChange":6.708519366316887},{"symbol":"SHRIRAMFIN","series":"EQ","comapnyName":"Shriram Finance Limited","new52WHL":3337.9,"prev52WHL":3323.2,"prevHLDate":"09-Sep-2024","ltp":3256.05,"prevClose":"3315.7","change":-59.65,"pChange":-1.799016798866001},{"symbol":"SILKFLEX","series":"SM","comapnyName":"Silkflex Polymers (India) Limited","new52WHL":98.7,"prev52WHL":98,"prevHLDate":"30-Jul-2024","ltp":98.7,"prevClose":"89.75","change":8.95,"pChange":9.972144846796658},{"symbol":"SIMPLEXINF","series":"EQ","comapnyName":"Simplex Infrastructures Limited","new52WHL":189.01,"prev52WHL":180.01,"prevHLDate":"09-Sep-2024","ltp":189.01,"prevClose":"180.01","change":9,"pChange":4.999722237653463},{"symbol":"SJLOGISTIC","series":"SM","comapnyName":"S J Logistics (India) Limited","new52WHL":674.5,"prev52WHL":670,"prevHLDate":"09-Sep-2024","ltp":645,"prevClose":"648.45","change":-3.45,"pChange":-0.5320379366180893},{"symbol":"SOLARA","series":"BE","comapnyName":"Solara Active Pharma Sciences Limited","new52WHL":814,"prev52WHL":784.15,"prevHLDate":"09-Sep-2024","ltp":760,"prevClose":"784.1","change":-24.1,"pChange":-3.073587552608086},{"symbol":"STEELCAS","series":"EQ","comapnyName":"Steelcast Limited","new52WHL":790,"prev52WHL":785.4,"prevHLDate":"06-Sep-2024","ltp":750.05,"prevClose":"752.4","change":-2.35,"pChange":-0.3123338649654439},{"symbol":"STEL","series":"BE","comapnyName":"Stel Holdings Limited","new52WHL":582.6,"prev52WHL":572,"prevHLDate":"09-Sep-2024","ltp":564.8,"prevClose":"556.2","change":8.6,"pChange":1.5462064005753327},{"symbol":"SUKHJITS","series":"EQ","comapnyName":"Sukhjit Starch & Chemicals Limited","new52WHL":628.8,"prev52WHL":597.9,"prevHLDate":"09-Jan-2024","ltp":607,"prevClose":"566.4","change":40.6,"pChange":7.168079096045198},{"symbol":"SUMICHEM","series":"EQ","comapnyName":"Sumitomo Chemical India Limited","new52WHL":628.3,"prev52WHL":567.35,"prevHLDate":"22-Aug-2024","ltp":611.5,"prevClose":"531.8","change":79.7,"pChange":14.986837156825874},{"symbol":"SUMMITSEC","series":"EQ","comapnyName":"Summit Securities Limited","new52WHL":2798.7,"prev52WHL":2549.95,"prevHLDate":"28-Aug-2024","ltp":2734,"prevClose":"2423.2","change":310.8,"pChange":12.826015186530208},{"symbol":"SUNDRMBRAK","series":"BE","comapnyName":"Sundaram Brake Linings Limited","new52WHL":1260,"prev52WHL":1220.15,"prevHLDate":"09-Sep-2024","ltp":1218.95,"prevClose":"1200.3","change":18.65,"pChange":1.553778222111139},{"symbol":"SUVENPHAR","series":"EQ","comapnyName":"Suven Pharmaceuticals Limited","new52WHL":1257,"prev52WHL":1225,"prevHLDate":"09-Sep-2024","ltp":1192.05,"prevClose":"1206","change":-13.95,"pChange":-1.1567164179104477},{"symbol":"SUYOG","series":"EQ","comapnyName":"Suyog Telematics Limited","new52WHL":1777.4,"prev52WHL":1735.25,"prevHLDate":"28-Aug-2024","ltp":1729,"prevClose":"1700.8","change":28.2,"pChange":1.6580432737535278},{"symbol":"SYNCOMF","series":"EQ","comapnyName":"Syncom Formulations (India) Limited","new52WHL":27.9,"prev52WHL":27.45,"prevHLDate":"09-Sep-2024","ltp":26.06,"prevClose":"26.77","change":-0.71,"pChange":-2.6522226372805378},{"symbol":"SYNGENE","series":"EQ","comapnyName":"Syngene International Limited","new52WHL":938,"prev52WHL":924,"prevHLDate":"05-Sep-2024","ltp":929.5,"prevClose":"894.25","change":35.25,"pChange":3.941850712887895},{"symbol":"TBZ","series":"EQ","comapnyName":"Tribhovandas Bhimji Zaveri Limited","new52WHL":284.85,"prev52WHL":275.9,"prevHLDate":"09-Sep-2024","ltp":268,"prevClose":"270.37","change":-2.37,"pChange":-0.8765765432555387},{"symbol":"TEMBO","series":"BE","comapnyName":"Tembo Global Industries Limited","new52WHL":425,"prev52WHL":417.95,"prevHLDate":"05-Sep-2024","ltp":399,"prevClose":"404.9","change":-5.9,"pChange":-1.4571499135589034},{"symbol":"TGL","series":"ST","comapnyName":"Teerth Gopicon Limited","new52WHL":774,"prev52WHL":740.7,"prevHLDate":"09-Sep-2024","ltp":703.7,"prevClose":"740.7","change":-37,"pChange":-4.995274740110706},{"symbol":"TI","series":"EQ","comapnyName":"Tilaknagar Industries Limited","new52WHL":325.5,"prev52WHL":314.5,"prevHLDate":"05-Sep-2024","ltp":324.9,"prevClose":"300.65","change":24.25,"pChange":8.06585730916348},{"symbol":"TRIVENI","series":"EQ","comapnyName":"Triveni Engineering & Industries Limited","new52WHL":487,"prev52WHL":484,"prevHLDate":"30-Aug-2024","ltp":463.2,"prevClose":"465.25","change":-2.05,"pChange":-0.44062332079527133},{"symbol":"TTKHLTCARE","series":"EQ","comapnyName":"TTK Healthcare Limited","new52WHL":1893.95,"prev52WHL":1853,"prevHLDate":"09-Sep-2024","ltp":1832.1,"prevClose":"1843.1","change":-11,"pChange":-0.5968205740328794},{"symbol":"UDS","series":"EQ","comapnyName":"Updater Services Limited","new52WHL":396.6,"prev52WHL":389.45,"prevHLDate":"05-Sep-2024","ltp":384,"prevClose":"380.25","change":3.75,"pChange":0.9861932938856016},{"symbol":"UNITDSPR","series":"EQ","comapnyName":"United Spirits Limited","new52WHL":1519.75,"prev52WHL":1514,"prevHLDate":"05-Sep-2024","ltp":1506.5,"prevClose":"1504.05","change":2.45,"pChange":0.16289352082710015},{"symbol":"UTSSAV","series":"SM","comapnyName":"Utssav CZ Gold Jewels Limited","new52WHL":247.8,"prev52WHL":227.8,"prevHLDate":"27-Aug-2024","ltp":239.95,"prevClose":"216.15","change":23.8,"pChange":11.01087207957437},{"symbol":"VIMTALABS","series":"EQ","comapnyName":"Vimta Labs Limited","new52WHL":699.8,"prev52WHL":683,"prevHLDate":"09-Sep-2024","ltp":641,"prevClose":"675.15","change":-34.15,"pChange":-5.058135229208324},{"symbol":"VOLTAS","series":"EQ","comapnyName":"Voltas Limited","new52WHL":1837.9,"prev52WHL":1828.75,"prevHLDate":"03-Sep-2024","ltp":1822.15,"prevClose":"1817.95","change":4.2,"pChange":0.2310294562556726},{"symbol":"WEBELSOLAR","series":"BE","comapnyName":"Websol Energy System Limited","new52WHL":1179,"prev52WHL":1143.8,"prevHLDate":"09-Sep-2024","ltp":1100,"prevClose":"1143.8","change":-43.8,"pChange":-3.829340793845078}],"timestamp":"10-Sep-2024 15:30:27"}