{"high":56,"data":[{"symbol":"ABREL","series":"EQ","comapnyName":"Aditya Birla Real Estate Limited","new52WHL":3125,"prev52WHL":2967,"prevHLDate":"16-Oct-2024","ltp":3039.95,"prevClose":"2856","change":183.95,"pChange":6.440826330532213},{"symbol":"ANANDRATHI","series":"EQ","comapnyName":"Anand Rathi Wealth Limited","new52WHL":4374.65,"prev52WHL":4299.95,"prevHLDate":"03-Jun-2024","ltp":4299,"prevClose":"4078.1","change":227.9,"pChange":5.597995627717324},{"symbol":"ARIHANTACA","series":"ST","comapnyName":"Arihant Academy Limited","new52WHL":230,"prev52WHL":229.3,"prevHLDate":"16-Oct-2024","ltp":229.5,"prevClose":"229","change":0.5,"pChange":0.2183406113537118},{"symbol":"BANARBEADS","series":"EQ","comapnyName":"Banaras Beads Limited","new52WHL":154,"prev52WHL":132.34,"prevHLDate":"17-Oct-2024","ltp":140,"prevClose":"132.34","change":7.66,"pChange":5.7881215052138435},{"symbol":"BLUECHIP","series":"BE","comapnyName":"Blue Chip India Limited","new52WHL":7.07,"prev52WHL":6.94,"prevHLDate":"17-Oct-2024","ltp":7.07,"prevClose":"6.94","change":0.13,"pChange":1.8731988472622478},{"symbol":"CARTRADE","series":"EQ","comapnyName":"Cartrade Tech Limited","new52WHL":1054.6,"prev52WHL":1041.9,"prevHLDate":"17-Oct-2024","ltp":1045,"prevClose":"1015.85","change":29.15,"pChange":2.8695181375203034},{"symbol":"CHOICEIN","series":"EQ","comapnyName":"Choice International Limited","new52WHL":497.8,"prev52WHL":494.9,"prevHLDate":"17-Oct-2024","ltp":491.3,"prevClose":"480","change":11.3,"pChange":2.3541666666666665},{"symbol":"CREATIVEYE","series":"EQ","comapnyName":"Creative Eye Limited","new52WHL":9.04,"prev52WHL":8.61,"prevHLDate":"17-Oct-2024","ltp":9.04,"prevClose":"8.61","change":0.43,"pChange":4.994192799070848},{"symbol":"DIACABS","series":"BE","comapnyName":"Diamond Power Infrastructure Limited","new52WHL":1899.95,"prev52WHL":1831.95,"prevHLDate":"17-Oct-2024","ltp":1849.95,"prevClose":"1817.9","change":32.05,"pChange":1.763023268606634},{"symbol":"DICIND","series":"BE","comapnyName":"DIC India Limited","new52WHL":801.9,"prev52WHL":795,"prevHLDate":"17-Oct-2024","ltp":799.5,"prevClose":"778.8","change":20.7,"pChange":2.657935285053929},{"symbol":"DIFFNKG","series":"EQ","comapnyName":"Diffusion Engineers Limited","new52WHL":351.45,"prev52WHL":299.01,"prevHLDate":"17-Oct-2024","ltp":338.2,"prevClose":"299.01","change":39.19,"pChange":13.106585064044681},{"symbol":"DOMS","series":"EQ","comapnyName":"DOMS Industries Limited","new52WHL":3038.6,"prev52WHL":2975,"prevHLDate":"17-Sep-2024","ltp":2924,"prevClose":"2790","change":134,"pChange":4.802867383512544},{"symbol":"E2E","series":"BE","comapnyName":"E2E Networks Limited","new52WHL":3829.65,"prev52WHL":3829,"prevHLDate":"17-Oct-2024","ltp":3829.65,"prevClose":"3647.3","change":182.35,"pChange":4.999588736873852},{"symbol":"EFACTOR","series":"SM","comapnyName":"E Factor Experiences Limited","new52WHL":294,"prev52WHL":289,"prevHLDate":"17-Oct-2024","ltp":287.9,"prevClose":"284.35","change":3.55,"pChange":1.2484614032002814},{"symbol":"GLOBALPET","series":"SM","comapnyName":"Global Pet Industries Limited","new52WHL":136,"prev52WHL":136,"prevHLDate":"16-Oct-2024","ltp":134,"prevClose":"130.15","change":3.85,"pChange":2.9581252401075684},{"symbol":"GOLD1","series":"EQ","comapnyName":"Kotak Mutual Fund - Gold Exchange Traded Fund","new52WHL":65.65,"prev52WHL":65.04,"prevHLDate":"01-Oct-2024","ltp":65.6,"prevClose":"64.84","change":0.76,"pChange":1.1721159777914867},{"symbol":"GOLDBEES","series":"EQ","comapnyName":"NIPPON INDIA ETF GOLD BEES","new52WHL":65.6,"prev52WHL":65.45,"prevHLDate":"01-Oct-2024","ltp":65.2,"prevClose":"64.44","change":0.76,"pChange":1.1793916821849784},{"symbol":"GOLDIETF","series":"EQ","comapnyName":"ICICI Prudential Gold ETF","new52WHL":69.72,"prev52WHL":68.8,"prevHLDate":"03-Oct-2024","ltp":67.26,"prevClose":"66.48","change":0.78,"pChange":1.1732851985559567},{"symbol":"GOLDSHARE","series":"EQ","comapnyName":"UTI Mutual Fund - UTI Gold Exchange Traded Fund","new52WHL":65.8,"prev52WHL":65.65,"prevHLDate":"04-Oct-2024","ltp":65.65,"prevClose":"65.1","change":0.55,"pChange":0.8448540706605223},{"symbol":"GOPAL","series":"EQ","comapnyName":"Gopal Snacks Limited","new52WHL":487,"prev52WHL":481,"prevHLDate":"16-Oct-2024","ltp":471.85,"prevClose":"467.05","change":4.8,"pChange":1.0277272240659459},{"symbol":"GREAVESCOT","series":"EQ","comapnyName":"Greaves Cotton Limited","new52WHL":197.65,"prev52WHL":196.37,"prevHLDate":"17-Oct-2024","ltp":193.63,"prevClose":"188.99","change":4.64,"pChange":2.4551563574792317},{"symbol":"HDFCQUAL","series":"EQ","comapnyName":"HDFC Mutual Fund - HDFC NIFTY100 Quality 30 ETF","new52WHL":66.03,"prev52WHL":65.7,"prevHLDate":"30-Sep-2024","ltp":63,"prevClose":"63.19","change":-0.19,"pChange":-0.3006804874188954},{"symbol":"HIRECT","series":"EQ","comapnyName":"Hind Rectifiers Limited","new52WHL":1174.65,"prev52WHL":1067.9,"prevHLDate":"17-Oct-2024","ltp":1174.65,"prevClose":"1067.9","change":106.75,"pChange":9.996254330929862},{"symbol":"HVAX","series":"ST","comapnyName":"HVAX Technologies Limited","new52WHL":691.65,"prev52WHL":658.75,"prevHLDate":"17-Oct-2024","ltp":691.65,"prevClose":"658.75","change":32.9,"pChange":4.9943074003795065},{"symbol":"IIFLSEC","series":"EQ","comapnyName":"IIFL Securities Limited","new52WHL":448.95,"prev52WHL":445.55,"prevHLDate":"17-Oct-2024","ltp":443.75,"prevClose":"432.35","change":11.4,"pChange":2.6367526309702787},{"symbol":"INDOTECH","series":"BE","comapnyName":"Indo Tech Transformers Limited","new52WHL":2624.6,"prev52WHL":2499.65,"prevHLDate":"17-Oct-2024","ltp":2520,"prevClose":"2499.65","change":20.35,"pChange":0.8141139759566339},{"symbol":"INFOLLION","series":"SM","comapnyName":"Infollion Research Services Limited","new52WHL":385,"prev52WHL":367.65,"prevHLDate":"17-Oct-2024","ltp":382,"prevClose":"367.65","change":14.35,"pChange":3.903168774649803},{"symbol":"INTERARCH","series":"EQ","comapnyName":"Interarch Building Products Limited","new52WHL":1705,"prev52WHL":1671,"prevHLDate":"15-Oct-2024","ltp":1692.45,"prevClose":"1602.2","change":90.25,"pChange":5.632879790288354},{"symbol":"JSWHL","series":"EQ","comapnyName":"JSW Holdings Limited","new52WHL":9822,"prev52WHL":9600,"prevHLDate":"17-Oct-2024","ltp":9300,"prevClose":"9540.1","change":-240.1,"pChange":-2.516745107493632},{"symbol":"KICL","series":"EQ","comapnyName":"Kalyani Investment Company Limited","new52WHL":7466.2,"prev52WHL":7127.6,"prevHLDate":"17-Oct-2024","ltp":7466.2,"prevClose":"7110.7","change":355.5,"pChange":4.999507784043765},{"symbol":"LIBERTSHOE","series":"BE","comapnyName":"Liberty Shoes Limited","new52WHL":569.6,"prev52WHL":569.45,"prevHLDate":"17-Oct-2024","ltp":560,"prevClose":"569.45","change":-9.45,"pChange":-1.659496004917025},{"symbol":"LIQUIDCASE","series":"EQ","comapnyName":"Zerodha Fund House - Zerodha Nifty 1D Rate Liquid ETF","new52WHL":108,"prev52WHL":107.95,"prevHLDate":"16-Oct-2024","ltp":104.93,"prevClose":"104.87","change":0.06,"pChange":0.057213693143892436},{"symbol":"LIQUIDSBI","series":"EQ","comapnyName":"SBI Mutual Fund - SBI NIFTY 1D Rate ETF","new52WHL":1000.01,"prev52WHL":1000.01,"prevHLDate":"17-Oct-2024","ltp":1000.01,"prevClose":"1000","change":0.01,"pChange":0.001},{"symbol":"MCX","series":"EQ","comapnyName":"Multi Commodity Exchange of India Limited","new52WHL":6605.95,"prev52WHL":6590,"prevHLDate":"16-Oct-2024","ltp":6575,"prevClose":"6341.45","change":233.55,"pChange":3.6829116369284627},{"symbol":"MOTILALOFS","series":"EQ","comapnyName":"Motilal Oswal Financial Services Limited","new52WHL":1064,"prev52WHL":988.1,"prevHLDate":"16-Oct-2024","ltp":1023.5,"prevClose":"929.4","change":94.1,"pChange":10.124811706477297},{"symbol":"MUNJALAU","series":"EQ","comapnyName":"Munjal Auto Industries Limited","new52WHL":145.7,"prev52WHL":143.6,"prevHLDate":"16-Oct-2024","ltp":143.95,"prevClose":"137.37","change":6.58,"pChange":4.78998325689743},{"symbol":"NATIONALUM","series":"EQ","comapnyName":"National Aluminium Company Limited","new52WHL":232.8,"prev52WHL":232.45,"prevHLDate":"14-Oct-2024","ltp":231.72,"prevClose":"225.17","change":6.55,"pChange":2.908913265532709},{"symbol":"NITCO","series":"EQ","comapnyName":"Nitco Limited","new52WHL":121.3,"prev52WHL":115.53,"prevHLDate":"17-Oct-2024","ltp":121.3,"prevClose":"115.53","change":5.77,"pChange":4.994373755734442},{"symbol":"NSIL","series":"EQ","comapnyName":"Nalwa Sons Investments Limited","new52WHL":7350,"prev52WHL":6363,"prevHLDate":"17-Oct-2024","ltp":7075,"prevClose":"6251.5","change":823.5,"pChange":13.1728385187555},{"symbol":"PENIND","series":"EQ","comapnyName":"Pennar Industries Limited","new52WHL":210.35,"prev52WHL":204.12,"prevHLDate":"30-Jul-2024","ltp":207.01,"prevClose":"185.87","change":21.14,"pChange":11.373540646688546},{"symbol":"PILANIINVS","series":"EQ","comapnyName":"Pilani Investment and Industries Corporation Limited","new52WHL":6340,"prev52WHL":5899,"prevHLDate":"15-Oct-2024","ltp":6270,"prevClose":"5743.15","change":526.85,"pChange":9.173537170368178},{"symbol":"PRANIK","series":"ST","comapnyName":"Pranik Logistics Limited","new52WHL":87.05,"prev52WHL":82.95,"prevHLDate":"17-Oct-2024","ltp":87.05,"prevClose":"82.95","change":4.1,"pChange":4.942736588306208},{"symbol":"PRIMESECU","series":"EQ","comapnyName":"Prime Securities Limited","new52WHL":339.9,"prev52WHL":329.95,"prevHLDate":"17-Oct-2024","ltp":331.5,"prevClose":"327.4","change":4.1,"pChange":1.2522907758094075},{"symbol":"PRIVISCL","series":"EQ","comapnyName":"Privi Speciality Chemicals Limited","new52WHL":1779.9,"prev52WHL":1720,"prevHLDate":"29-Jul-2024","ltp":1756.3,"prevClose":"1691.4","change":64.9,"pChange":3.837058058413149},{"symbol":"RGL","series":"EQ","comapnyName":"Renaissance Global Limited","new52WHL":184,"prev52WHL":179.9,"prevHLDate":"17-Oct-2024","ltp":182,"prevClose":"176.88","change":5.12,"pChange":2.8946178199909545},{"symbol":"RITCO","series":"EQ","comapnyName":"Ritco Logistics Limited","new52WHL":409,"prev52WHL":406.7,"prevHLDate":"17-Oct-2024","ltp":392,"prevClose":"401.1","change":-9.1,"pChange":-2.268760907504363},{"symbol":"RPEL","series":"EQ","comapnyName":"Raghav Productivity Enhancers Limited","new52WHL":1415,"prev52WHL":1390,"prevHLDate":"17-Oct-2024","ltp":1263,"prevClose":"1329.7","change":-66.7,"pChange":-5.016169060690381},{"symbol":"SAHASRA","series":"SM","comapnyName":"Sahasra Electronic Solutions Limited","new52WHL":883.9,"prev52WHL":872.25,"prevHLDate":"17-Oct-2024","ltp":760,"prevClose":"872.25","change":-112.25,"pChange":-12.869016910289481},{"symbol":"SEJALLTD","series":"EQ","comapnyName":"Sejal Glass Limited","new52WHL":494.3,"prev52WHL":487.7,"prevHLDate":"08-Oct-2024","ltp":494.3,"prevClose":"470.8","change":23.5,"pChange":4.991503823279524},{"symbol":"SILINV","series":"EQ","comapnyName":"SIL Investments Limited","new52WHL":743.05,"prev52WHL":689,"prevHLDate":"16-Oct-2024","ltp":730,"prevClose":"643.1","change":86.9,"pChange":13.5126729902037},{"symbol":"SOLARA","series":"EQ","comapnyName":"Solara Active Pharma Sciences Limited","new52WHL":844,"prev52WHL":830,"prevHLDate":"26-Sep-2024","ltp":807.05,"prevClose":"803.85","change":3.2,"pChange":0.3980842196927287},{"symbol":"TORNTPOWER","series":"EQ","comapnyName":"Torrent Power Limited","new52WHL":1993,"prev52WHL":1984.7,"prevHLDate":"09-Oct-2024","ltp":1972,"prevClose":"1939.8","change":32.2,"pChange":1.6599649448396743},{"symbol":"UNIVASTU","series":"EQ","comapnyName":"Univastu India Limited","new52WHL":250.5,"prev52WHL":239.73,"prevHLDate":"27-Sep-2024","ltp":250.5,"prevClose":"238.58","change":11.92,"pChange":4.996227680442619},{"symbol":"VINCOFE","series":"EQ","comapnyName":"Vintage Coffee And Beverages Limited","new52WHL":142.1,"prev52WHL":0,"prevHLDate":"-","ltp":140.8,"prevClose":"133.3","change":7.5,"pChange":5.626406601650412},{"symbol":"VPRPL","series":"EQ","comapnyName":"Vishnu Prakash R Punglia Limited","new52WHL":324.85,"prev52WHL":306.85,"prevHLDate":"16-Oct-2024","ltp":315.55,"prevClose":"285.05","change":30.5,"pChange":10.699877214523768},{"symbol":"WABAG","series":"EQ","comapnyName":"VA Tech Wabag Limited","new52WHL":1905.65,"prev52WHL":1827.65,"prevHLDate":"17-Oct-2024","ltp":1897.1,"prevClose":"1777.9","change":119.2,"pChange":6.704539062939423}],"timestamp":"18-Oct-2024 15:40:56"}